{"problem_id":22,"musicians":[{"placement":{"x":622.2838524621634,"y":10.0},"volume":1.0,"instrument":0,"score":650052},{"placement":{"x":442.25435746363496,"y":10.0},"volume":1.0,"instrument":1,"score":565003},{"placement":{"x":191.9385401906524,"y":10.0},"volume":1.0,"instrument":2,"score":1196351},{"placement":{"x":678.19588759253,"y":10.0},"volume":1.0,"instrument":3,"score":822856},{"placement":{"x":87.07758496929429,"y":10.0},"volume":1.0,"instrument":4,"score":1564295},{"placement":{"x":749.7460105553209,"y":10.0},"volume":1.0,"instrument":5,"score":1367064},{"placement":{"x":259.62481189181915,"y":10.0},"volume":1.0,"instrument":6,"score":542111},{"placement":{"x":469.5989397160772,"y":10.0},"volume":1.0,"instrument":7,"score":1232297},{"placement":{"x":162.38852413570095,"y":10.0},"volume":1.0,"instrument":8,"score":1088488},{"placement":{"x":701.8282313082816,"y":10.0},"volume":1.0,"instrument":2,"score":4115677},{"placement":{"x":105.13250799724284,"y":10.0},"volume":1.0,"instrument":3,"score":2646977},{"placement":{"x":310.76907528680374,"y":10.0},"volume":1.0,"instrument":6,"score":687347},{"placement":{"x":544.0628423892214,"y":10.0},"volume":1.0,"instrument":1,"score":848174},{"placement":{"x":60.2187030683789,"y":10.0},"volume":1.0,"instrument":0,"score":1441441},{"placement":{"x":661.2414971958829,"y":10.0},"volume":1.0,"instrument":1,"score":1462240},{"placement":{"x":969.1664194629647,"y":10.0},"volume":1.0,"instrument":3,"score":1006181}],"elapsed_time":0.00023513,"score":21236554}