{"problem_id":26,"musicians":[{"placement":{"x":215.32155782079383,"y":10.0},"volume":1.0,"instrument":0,"score":5252972},{"placement":{"x":954.0791310122337,"y":10.0},"volume":1.0,"instrument":1,"score":2804187},{"placement":{"x":785.0296096888276,"y":10.0},"volume":1.0,"instrument":2,"score":5513615},{"placement":{"x":672.5704157486206,"y":10.0},"volume":1.0,"instrument":3,"score":6568986},{"placement":{"x":279.59266444365477,"y":10.0},"volume":1.0,"instrument":4,"score":3102135},{"placement":{"x":616.2471300240917,"y":10.0},"volume":1.0,"instrument":5,"score":3347822},{"placement":{"x":741.6083295116839,"y":10.0},"volume":1.0,"instrument":6,"score":3294443},{"placement":{"x":722.3613312315864,"y":10.0},"volume":1.0,"instrument":7,"score":4078604},{"placement":{"x":516.6704176354124,"y":10.0},"volume":1.0,"instrument":8,"score":3012300},{"placement":{"x":644.1501629522735,"y":10.0},"volume":1.0,"instrument":9,"score":4992513},{"placement":{"x":988.5606855963265,"y":10.0},"volume":1.0,"instrument":4,"score":1907168},{"placement":{"x":364.2388903861232,"y":10.0},"volume":1.0,"instrument":9,"score":1795550},{"placement":{"x":67.18369412595987,"y":10.0},"volume":1.0,"instrument":0,"score":5341762},{"placement":{"x":445.6129623105296,"y":10.0},"volume":1.0,"instrument":8,"score":9896868},{"placement":{"x":850.8046071421911,"y":10.0},"volume":1.0,"instrument":9,"score":1220315}],"elapsed_time":0.001229669,"score":62129240}